LICENSE
MANIFEST.in
README.md
setup.py
pypysodium.egg-info/PKG-INFO
pypysodium.egg-info/SOURCES.txt
pypysodium.egg-info/dependency_links.txt
pypysodium.egg-info/top_level.txt
sodium/__init__.py
sodium/client.py