Metadata-Version: 2.1
Name: pypysodium
Version: 1.0.0
Summary: Pythonic Music Player
Home-page: UNKNOWN
License: MIT
Keywords: music,python,player,ytdl
Platform: UNKNOWN
Classifier: Development Status :: 1 - Planning
Classifier: License :: OSI Approved :: MIT License
Classifier: Topic :: Multimedia :: Sound/Audio
Classifier: Topic :: Multimedia :: Sound/Audio :: Players
Classifier: Topic :: Multimedia :: Sound/Audio :: Players :: MP3
Classifier: Typing :: Typed
License-File: LICENSE
